vtclear/__init__.py
vtclear/vtclear.py
vtclear-1.0.dist-info/LICENSE
vtclear-1.0.dist-info/METADATA
vtclear-1.0.dist-info/WHEEL
vtclear-1.0.dist-info/top_level.txt
vtclear-1.0.dist-info/RECORD
